WebView2Loader.dll
screamrouter_audio_engine.cp311-win_amd64.pyd
screamrouter/__init__.py
screamrouter/__main__.py
screamrouter/uvicorn_log_config.yaml
screamrouter/api/__init__.py
screamrouter/api/api_configuration.py
screamrouter/api/api_equalizer.py
screamrouter/api/api_log_viewer.py
screamrouter/api/api_mdns.py
screamrouter/api/api_neighbors.py
screamrouter/api/api_preferences.py
screamrouter/api/api_stats.py
screamrouter/api/api_system.py
screamrouter/api/api_timeshift.py
screamrouter/api/api_vnc_websocket.py
screamrouter/api/api_webrtc.py
screamrouter/api/api_website.py
screamrouter/api/api_websocket_config.py
screamrouter/api/api_websocket_debug.py
screamrouter/api/api_webstream.py
screamrouter/api/timeshift_client.py
screamrouter/audio/__init__.py
screamrouter/audio/scream_header_parser.py
screamrouter/configuration/__init__.py
screamrouter/configuration/configuration_manager.py
screamrouter/configuration/configuration_solver.py
screamrouter/configuration/temporary_entity_manager.py
screamrouter/constants/__init__.py
screamrouter/constants/constants.py
screamrouter/plugin_manager/__init__.py
screamrouter/plugin_manager/plugin_manager.py
screamrouter/plugin_manager/screamrouter_plugin.py
screamrouter/plugins/__init__.py
screamrouter/plugins/play_url.py
screamrouter/plugins/play_url_multiple.py
screamrouter/preferences/__init__.py
screamrouter/preferences/preferences_manager.py
screamrouter/screamrouter_logger/__init__.py
screamrouter/screamrouter_logger/screamrouter_logger.py
screamrouter/screamrouter_types/__init__.py
screamrouter/screamrouter_types/annotations.py
screamrouter/screamrouter_types/configuration.py
screamrouter/screamrouter_types/exceptions.py
screamrouter/screamrouter_types/mdns.py
screamrouter/screamrouter_types/packets.py
screamrouter/screamrouter_types/preferences.py
screamrouter/screamrouter_types/website.py
screamrouter/site/364.07f898e2066bda2556a1.js
screamrouter/site/52.923e4b69f01207801da8.js
screamrouter-0.3.75.dist-info/METADATA
screamrouter-0.3.75.dist-info/WHEEL
screamrouter-0.3.75.dist-info/entry_points.txt
screamrouter-0.3.75.dist-info/top_level.txt
screamrouter-0.3.75.dist-info/RECORD
