Metadata-Version: 2.4
Name: screamrouter
Version: 0.3.75
Summary: ScreamRouter audio routing system with web interface and C++ audio engine
Author: Netham45
License: AGPL-3.0
Project-URL: Homepage, https://github.com/netham45/screamrouter
Project-URL: Repository, https://github.com/netham45/screamrouter
Project-URL: Issues, https://github.com/netham45/screamrouter/issues
Keywords: audio,routing,scream,network,streaming,webrtc
Classifier: Development Status :: 4 - Beta
Classifier: Intended Audience :: Developers
Classifier: Programming Language :: Python :: 3
Classifier: Programming Language :: Python :: 3.10
Classifier: Programming Language :: Python :: 3.11
Classifier: Programming Language :: Python :: 3.12
Classifier: Programming Language :: Python :: 3.13
Classifier: Programming Language :: Python :: 3.14
Classifier: Programming Language :: C++
Classifier: Operating System :: Microsoft :: Windows
Classifier: Operating System :: POSIX :: Linux
Classifier: Topic :: Multimedia :: Sound/Audio
Requires-Python: >=3.10
License-File: COPYING
Requires-Dist: pybind11>=2.6
Requires-Dist: pybind11-stubgen
Requires-Dist: cryptography
Requires-Dist: dnspython
Requires-Dist: fastapi
Requires-Dist: httpx
Requires-Dist: Jinja2
Requires-Dist: numpy
Requires-Dist: pydantic
Requires-Dist: pyOpenSSL
Requires-Dist: PyYAML
Requires-Dist: setproctitle
Requires-Dist: starlette
Requires-Dist: uvicorn
Requires-Dist: websockets
Requires-Dist: zeroconf
Provides-Extra: dev
Requires-Dist: pytest; extra == "dev"
Requires-Dist: pytest-cov; extra == "dev"
Requires-Dist: black; extra == "dev"
Requires-Dist: flake8; extra == "dev"
Requires-Dist: mypy; extra == "dev"
Dynamic: license-file
Dynamic: requires-python
